teth/__init__.py
teth/_utils.py
teth-0.1.0.dist-info/METADATA
teth-0.1.0.dist-info/WHEEL
teth-0.1.0.dist-info/entry_points.txt
teth-0.1.0.dist-info/licenses/LICENSE
teth-0.1.0.dist-info/RECORD
