Metadata-Version: 2.4
Name: teth
Version: 0.1.0
Summary: JSon-RPC client for EthereumTesterProvider
Author-email: Stuart Reed <stuart.reed@ethereum.org>
License-File: LICENSE
Requires-Python: >=3.10
Requires-Dist: click>=8.1.8
Requires-Dist: eth-tester>=0.12.1b1
Requires-Dist: flask>=3.1.0
Requires-Dist: web3[tester]>=7.10.0
